egeometry/__init__.py
egeometry/_dboundingbox2d.hpp
egeometry/_dboundingbox2d.py
egeometry/_dboundingbox2dtype.hpp
egeometry/_dboundingbox3d.py
egeometry/_dcircle.py
egeometry/_dlinesegment3d.py
egeometry/_dplane.py
egeometry/_drectangle.py
egeometry/_drectanglefrustum.py
egeometry/_dtriangle2d.py
egeometry/_dtrianglemesh3d.py
egeometry/_egeometry.c
egeometry/_egeometry.cpp
egeometry/_egeometry.cpython-312-x86_64-linux-gnu.so
egeometry/_egeometry.pyi
egeometry/_fboundingbox2d.hpp
egeometry/_fboundingbox2d.py
egeometry/_fboundingbox2dtype.hpp
egeometry/_fboundingbox3d.py
egeometry/_fcircle.py
egeometry/_flinesegment3d.py
egeometry/_fplane.py
egeometry/_frectangle.py
egeometry/_frectanglefrustum.py
egeometry/_ftriangle2d.py
egeometry/_ftrianglemesh3d.py
egeometry/_iboundingbox2d.hpp
egeometry/_iboundingbox2d.py
egeometry/_iboundingbox2dtype.hpp
egeometry/_iboundingbox3d.py
egeometry/_icircle.py
egeometry/_irectangle.py
egeometry/_itriangle2d.py
egeometry/_module.hpp
egeometry/_modulestate.hpp
egeometry/_separating_axis_theorem.py
egeometry/py.typed
egeometry-0.20.1.dist-info/METADATA
egeometry-0.20.1.dist-info/WHEEL
egeometry-0.20.1.dist-info/RECORD
