Metadata-Version: 2.4
Name: egeometry
Version: 0.20.1
Summary: Python geometry library.
Author: Erik Soma
Author-email: stillusingirc@gmail.com
Requires-Python: >=3.12
Classifier: Programming Language :: Python :: 3
Classifier: Programming Language :: Python :: 3.12
Classifier: Programming Language :: Python :: 3.13
Classifier: Programming Language :: Python :: 3.14
Requires-Dist: emath (>=0,<1)
